{
  "version": 1,
  "license": "CC-BY-SA-3.0",
  "copyright": "Taken from CMSS13: https://github.com/cmss13-devs/cmss13/commit/dbebd43 | Revised for Goobstation by JohnJJohn (Github)",
  "size": {
    "x": 32,
    "y": 32
  },
  "states": [
    {
      "name": "xenomorph",
      "directions": 4
    },
    {
      "name": "xenomorph-moving",
      "directions": 4,
      "delays": [
        [
          0.2,
          0.2,
          0.2,
          0.2,
          0.2,
          0.2,
          0.2,
          0.2,
          0.2,
          0.2
        ],
        [
          0.2,
          0.2,
          0.2,
          0.2,
          0.2,
          0.2,
          0.2,
          0.2,
          0.2,
          0.2
        ],
        [
          0.2,
          0.2,
          0.2,
          0.2,
          0.2,
          0.2,
          0.2,
          0.2,
          0.2,
          0.2
        ],
        [
          0.2,
          0.2,
          0.2,
          0.2,
          0.2,
          0.2,
          0.2,
          0.2,
          0.2,
          0.2
        ]
      ]
    },
    {
      "name": "xenomorph_sleep",
      "delays": [
        [
          1,
          1
        ]
      ]
    },
    {
      "name": "xenomorph_unconscious",
      "delays": [
        [
          0.7,
          0.7
        ]
      ]
    },
    {
      "name": "xenomorph_dead"
    }
  ]
}

