{
    "version": 1,
    "license": "CC-BY-SA-3.0",
    "copyright": "Taken from tgstation, remade by CaypenNow",
    "size": {
        "x": 32,
        "y": 32
    },
    "states": [
        {
            "name": "icon",
            "delays": [
                [
                  0.1,
                  0.1,
                  0.1,
                  0.1
                ]
              ]
        },
        {
            "name": "inhand-left",
            "directions": 4
        },
        {
            "name": "inhand-right",
            "directions": 4
        },
        {
            "name": "in",
            "directions": 4,
            "delays": [
              [
                0.1,
                0.1,
                0.1,
                0.1,
                0.1,
                0.1,
                0.1,
                0.1
              ],
              [
                0.1,
                0.1,
                0.1,
                0.1,
                0.1,
                0.1,
                0.1,
                0.1
              ],
              [
                0.1,
                0.1,
                0.1,
                0.1,
                0.1,
                0.1,
                0.1,
                0.1
              ],
              [
                0.1,
                0.1,
                0.1,
                0.1,
                0.1,
                0.1,
                0.1,
                0.1
              ]
            ]
          },
          {
            "name": "out",
            "directions": 4,
            "delays": [
              [
                0.1,
                0.1,
                0.1,
                0.1,
                0.1,
                0.1,
                0.1,
                0.1
              ],
              [
                0.1,
                0.1,
                0.1,
                0.1,
                0.1,
                0.1,
                0.1,
                0.1
              ],
              [
                0.1,
                0.1,
                0.1,
                0.1,
                0.1,
                0.1,
                0.1,
                0.1
              ],
              [
                0.1,
                0.1,
                0.1,
                0.1,
                0.1,
                0.1,
                0.1,
                0.1
              ]
            ]
          }
    ]
}
